FinDataBroker/CLI.py
FinDataBroker/DataBrokerMongoDb.py
FinDataBroker/DataBrokerSqlite.py
FinDataBroker/IndexingMap.py
FinDataBroker/Template.py
FinDataBroker/__about__.py
FinDataBroker/__init__.py
FinDataBroker/tests/__init__.py
FinDataBroker/tests/test_CLI.py
FinDataBroker/tests/test_mongo.py
FinDataBroker/tests/test_sqlite.py
FinDataBroker-1.0.0a4.dist-info/LICENCE
FinDataBroker-1.0.0a4.dist-info/METADATA
FinDataBroker-1.0.0a4.dist-info/WHEEL
FinDataBroker-1.0.0a4.dist-info/entry_points.txt
FinDataBroker-1.0.0a4.dist-info/top_level.txt
FinDataBroker-1.0.0a4.dist-info/RECORD
