Metadata-Version: 2.1
Name: FinDataBroker
Version: 1.0.0a4
Summary: A databroker for financial data
Home-page: https://github.com/tomerten/findatabroker
Author: Tom Mertens
License: GNU General Public License v3.0
Platform: UNKNOWN
Classifier: Development Status :: 3 - Alpha
Classifier: Intended Audience :: Science/Research
Classifier: License :: OSI Approved :: GNU General Public License v3 (GPLv3)
Classifier: Programming Language :: Python :: 3.5
Classifier: Programming Language :: Python :: 3.6
Classifier: Programming Language :: Python :: 3.7
Classifier: Programming Language :: Python :: 3.8
Classifier: Programming Language :: Python :: Implementation :: CPython
Classifier: Programming Language :: Python :: Implementation :: PyPy
Classifier: Topic :: Office/Business :: Financial
Classifier: Intended Audience :: Financial and Insurance Industry
Requires-Python: >=3.6
Requires-Dist: click
Requires-Dist: pandas
Requires-Dist: h5py
Requires-Dist: termcolor
Requires-Dist: tables
Requires-Dist: xlsxwriter
Requires-Dist: xlrd
Requires-Dist: pymongo
Requires-Dist: mongomock
Requires-Dist: tqdm
Requires-Dist: dataset
Requires-Dist: financejson
